kannolo-0.3.7.dist-info/METADATA
kannolo-0.3.7.dist-info/WHEEL
kannolo-0.3.7.dist-info/licenses/LICENSE
kannolo/__init__.py
kannolo/kannolo.cpython-312-x86_64-linux-gnu.so
kannolo-0.3.7.dist-info/RECORD
