Metadata-Version: 2.4
Name: kannolo
Version: 0.3.7
Classifier: Programming Language :: Rust
Classifier: Programming Language :: Python :: Implementation :: CPython
Classifier: Programming Language :: Python :: Implementation :: PyPy
Classifier: License :: OSI Approved :: MIT License
Requires-Dist: numpy
License-File: LICENSE
Summary: Python interface for the kANNolo library
Keywords: Approximate Nearest Neighbors,Similarity Search,indexing,Rust
Author-email: Silvio Martinico <silvio.martinico@phd.unipi.it>, Leonardo Delfino <l.delfino1@studenti.unipi.it>, Domenico Erriquez <d.erriquez1@studenti.unipi.it>, Cosimo Rulli <cosimo.rulli@isti.cnr.it>, Franco Maria Nardini <francomaria.nardini@isti.cnr.it>, Rossano Venturini <rossano.venturini@unipi.it>
License: MIT
Requires-Python: >=3.7
Project-URL: Source Code, https://github.com/TusKANNy/kannolo
